simplex/__init__.py
simplex/__main__.py
simplex/bin/simplex_solver
simplex/bin/simplex_solver_nompi
simplex/src/common.js
simplex/src/constants.js
simplex/src/converter.js
simplex/src/guicomps.js
simplex/src/index.html
simplex/src/launch_solver.js
simplex/src/main.js
simplex/src/newplot.html
simplex/src/newplot.js
simplex/src/postprocess.js
simplex/src/preprocess.js
simplex/src/pythonui.js
simplex/src/simplex.css
simplex/src/simplex.html
simplex/src/simplex_solver.worker.js
simplex/src/simplex_solver_debug.worker.js
simplex/src/spectra.css
simplex/src/updategui.js
simplex/src/css/bootstrap-grid.css
simplex/src/css/bootstrap-grid.css.map
simplex/src/css/bootstrap-grid.min.css
simplex/src/css/bootstrap-grid.min.css.map
simplex/src/css/bootstrap-grid.rtl.css
simplex/src/css/bootstrap-grid.rtl.css.map
simplex/src/css/bootstrap-grid.rtl.min.css
simplex/src/css/bootstrap-grid.rtl.min.css.map
simplex/src/css/bootstrap-reboot.css
simplex/src/css/bootstrap-reboot.css.map
simplex/src/css/bootstrap-reboot.min.css
simplex/src/css/bootstrap-reboot.min.css.map
simplex/src/css/bootstrap-reboot.rtl.css
simplex/src/css/bootstrap-reboot.rtl.css.map
simplex/src/css/bootstrap-reboot.rtl.min.css
simplex/src/css/bootstrap-reboot.rtl.min.css.map
simplex/src/css/bootstrap-utilities.css
simplex/src/css/bootstrap-utilities.css.map
simplex/src/css/bootstrap-utilities.min.css
simplex/src/css/bootstrap-utilities.min.css.map
simplex/src/css/bootstrap-utilities.rtl.css
simplex/src/css/bootstrap-utilities.rtl.css.map
simplex/src/css/bootstrap-utilities.rtl.min.css
simplex/src/css/bootstrap-utilities.rtl.min.css.map
simplex/src/css/bootstrap.css
simplex/src/css/bootstrap.css.map
simplex/src/css/bootstrap.min.css
simplex/src/css/bootstrap.min.css.map
simplex/src/css/bootstrap.rtl.css
simplex/src/css/bootstrap.rtl.css.map
simplex/src/css/bootstrap.rtl.min.css
simplex/src/css/bootstrap.rtl.min.css.map
simplex/src/help/beamlet.png
simplex/src/help/dataimport.png
simplex/src/help/generate_header.js
simplex_ui-3.2.3.0.dist-info/METADATA
simplex_ui-3.2.3.0.dist-info/WHEEL
simplex_ui-3.2.3.0.dist-info/top_level.txt
simplex_ui-3.2.3.0.dist-info/RECORD
