Metadata-Version: 2.1
Name: simplex-ui
Version: 3.2.3.0
Summary: SIMPLEX User Interface to Python
Author: Takashi TANAKA
Author-email: admin@spectrax.org
License: MIT
Classifier: Programming Language :: C++
Classifier: Programming Language :: Python
Requires-Python: >=3.8
Requires-Dist: wheel
Requires-Dist: selenium>=4.6
Requires-Dist: pexpect
